{
  "2022": [
    {
      "name": "元旦",
      "holiday": [
        "1-1",
        "1-2",
        "1-3"
      ],
      "holidayFix": []
    },
    {
      "name": "春节",
      "holiday": [
        "1-31",
        "2-1",
        "2-2",
        "2-3",
        "2-4",
        "2-5",
        "2-6"
      ],
      "holidayFix": [
        "1-29",
        "1-30"
      ]
    },
    {
      "name": "清明节",
      "holiday": [
        "4-3",
        "4-4",
        "4-5"
      ],
      "holidayFix": [
        "4-2"
      ]
    },
    {
      "name": "劳动节",
      "holiday": [
        "4-30",
        "5-1",
        "5-2",
        "5-3",
        "5-4"
      ],
      "holidayFix": [
        "4-24",
        "5-7"
      ]
    },
    {
      "name": "端午节",
      "holiday": [
        "6-3",
        "6-4",
        "6-5"
      ],
      "holidayFix": []
    },
    {
      "name": "中秋节",
      "holiday": [
        "9-10",
        "9-11",
        "9-12"
      ],
      "holidayFix": []
    },
    {
      "name": "国庆节",
      "holiday": [
        "10-1",
        "10-2",
        "10-3",
        "10-4",
        "10-5",
        "10-6",
        "10-7"
      ],
      "holidayFix": [
        "10-8",
        "10-9"
      ]
    }
  ]
}